{
  "fio version" : "fio-3.28",
  "timestamp" : 1690470876,
  "timestamp_ms" : 1690470876990,
  "time" : "Thu Jul 27 15:14:36 2023",
  "global options" : {
    "bs" : "512k",
    "ioengine" : "libaio",
    "rw" : "randread",
    "size" : "10G",
    "name" : "test",
    "numjobs" : "32",
    "group_reporting" : "1",
    "iodepth" : "128",
    "fallocate" : "native",
    "runtime" : "120",
    "directory" : "/tmp/ssfs/home/sevag/fuse_ext4",
    "nrfiles" : "1"
  },
  "jobs" : [
    {
      "jobname" : "jobs1",
      "groupid" : 0,
      "error" : 0,
      "eta" : 0,
      "elapsed" : 33,
      "job options" : {
        "filename_format" : "f$filenum"
      },
      "read" : {
        "io_bytes" : 10737418240,
        "io_kbytes" : 10485760,
        "bw_bytes" : 336416901,
        "bw" : 328532,
        "iops" : 641.664317,
        "runtime" : 31917,
        "total_ios" : 20480,
        "short_ios" : 0,
        "drop_ios" : 0,
        "slat_ns" : {
          "min" : 979214,
          "max" : 2297973,
          "mean" : 1546666.127637,
          "stddev" : 129114.669890,
          "N" : 20480
        },
        "clat_ns" : {
          "min" : 5850,
          "max" : 234737533,
          "mean" : 197209028.554784,
          "stddev" : 12368577.662940,
          "N" : 20480,
          "percentile" : {
            "1.000000" : 177209344,
            "5.000000" : 185597952,
            "10.000000" : 189792256,
            "20.000000" : 191889408,
            "30.000000" : 191889408,
            "40.000000" : 193986560,
            "50.000000" : 196083712,
            "60.000000" : 198180864,
            "70.000000" : 200278016,
            "80.000000" : 210763776,
            "90.000000" : 210763776,
            "95.000000" : 210763776,
            "99.000000" : 210763776,
            "99.500000" : 212860928,
            "99.900000" : 229638144,
            "99.950000" : 233832448,
            "99.990000" : 233832448
          }
        },
        "lat_ns" : {
          "min" : 1429139,
          "max" : 236991353,
          "mean" : 198757075.127831,
          "stddev" : 12411197.655629,
          "N" : 20480
        },
        "bw_min" : 220893,
        "bw_max" : 360448,
        "bw_agg" : 99.543080,
        "bw_mean" : 327031.460317,
        "bw_dev" : 18663.779600,
        "bw_samples" : 63,
        "iops_min" : 431,
        "iops_max" : 704,
        "iops_mean" : 638.682540,
        "iops_stddev" : 36.485448,
        "iops_samples" : 63
      },
      "write" : {
        "io_bytes" : 0,
        "io_kbytes" : 0,
        "bw_bytes" : 0,
        "bw" : 0,
        "iops" : 0.000000,
        "runtime" : 0,
        "total_ios" : 0,
        "short_ios" : 0,
        "drop_ios" : 0,
        "slat_ns" : {
          "min" : 0,
          "max" : 0,
          "mean" : 0.000000,
          "stddev" : 0.000000,
          "N" : 0
        },
        "clat_ns" : {
          "min" : 0,
          "max" : 0,
          "mean" : 0.000000,
          "stddev" : 0.000000,
          "N" : 0
        },
        "lat_ns" : {
          "min" : 0,
          "max" : 0,
          "mean" : 0.000000,
          "stddev" : 0.000000,
          "N" : 0
        },
        "bw_min" : 0,
        "bw_max" : 0,
        "bw_agg" : 0.000000,
        "bw_mean" : 0.000000,
        "bw_dev" : 0.000000,
        "bw_samples" : 0,
        "iops_min" : 0,
        "iops_max" : 0,
        "iops_mean" : 0.000000,
        "iops_stddev" : 0.000000,
        "iops_samples" : 0
      },
      "trim" : {
        "io_bytes" : 0,
        "io_kbytes" : 0,
        "bw_bytes" : 0,
        "bw" : 0,
        "iops" : 0.000000,
        "runtime" : 0,
        "total_ios" : 0,
        "short_ios" : 0,
        "drop_ios" : 0,
        "slat_ns" : {
          "min" : 0,
          "max" : 0,
          "mean" : 0.000000,
          "stddev" : 0.000000,
          "N" : 0
        },
        "clat_ns" : {
          "min" : 0,
          "max" : 0,
          "mean" : 0.000000,
          "stddev" : 0.000000,
          "N" : 0
        },
        "lat_ns" : {
          "min" : 0,
          "max" : 0,
          "mean" : 0.000000,
          "stddev" : 0.000000,
          "N" : 0
        },
        "bw_min" : 0,
        "bw_max" : 0,
        "bw_agg" : 0.000000,
        "bw_mean" : 0.000000,
        "bw_dev" : 0.000000,
        "bw_samples" : 0,
        "iops_min" : 0,
        "iops_max" : 0,
        "iops_mean" : 0.000000,
        "iops_stddev" : 0.000000,
        "iops_samples" : 0
      },
      "sync" : {
        "total_ios" : 0,
        "lat_ns" : {
          "min" : 0,
          "max" : 0,
          "mean" : 0.000000,
          "stddev" : 0.000000,
          "N" : 0
        }
      },
      "job_runtime" : 31917,
      "usr_cpu" : 1.037065,
      "sys_cpu" : 33.944293,
      "ctx" : 81944,
      "majf" : 0,
      "minf" : 16465,
      "iodepth_level" : {
        "1" : 0.100000,
        "2" : 0.100000,
        "4" : 0.100000,
        "8" : 0.100000,
        "16" : 0.100000,
        "32" : 0.156250,
        ">=64" : 99.692383
      },
      "iodepth_submit" : {
        "0" : 0.000000,
        "4" : 100.000000,
        "8" : 0.000000,
        "16" : 0.000000,
        "32" : 0.000000,
        "64" : 0.000000,
        ">=64" : 0.000000
      },
      "iodepth_complete" : {
        "0" : 0.000000,
        "4" : 99.995087,
        "8" : 0.000000,
        "16" : 0.000000,
        "32" : 0.000000,
        "64" : 0.000000,
        ">=64" : 0.100000
      },
      "latency_ns" : {
        "2" : 0.000000,
        "4" : 0.000000,
        "10" : 0.000000,
        "20" : 0.000000,
        "50" : 0.000000,
        "100" : 0.000000,
        "250" : 0.000000,
        "500" : 0.000000,
        "750" : 0.000000,
        "1000" : 0.000000
      },
      "latency_us" : {
        "2" : 0.000000,
        "4" : 0.000000,
        "10" : 0.010000,
        "20" : 0.000000,
        "50" : 0.000000,
        "100" : 0.000000,
        "250" : 0.000000,
        "500" : 0.000000,
        "750" : 0.000000,
        "1000" : 0.000000
      },
      "latency_ms" : {
        "2" : 0.010000,
        "4" : 0.010000,
        "10" : 0.019531,
        "20" : 0.034180,
        "50" : 0.092773,
        "100" : 0.156250,
        "250" : 99.682617,
        "500" : 0.000000,
        "750" : 0.000000,
        "1000" : 0.000000,
        "2000" : 0.000000,
        ">=2000" : 0.000000
      },
      "latency_depth" : 128,
      "latency_target" : 0,
      "latency_percentile" : 100.000000,
      "latency_window" : 0
    }
  ]
}
