{
  "fio version" : "fio-3.28",
  "timestamp" : 1690480061,
  "timestamp_ms" : 1690480061263,
  "time" : "Thu Jul 27 17:47:41 2023",
  "global options" : {
    "bs" : "128k",
    "ioengine" : "libaio",
    "rw" : "randwrite",
    "size" : "30G",
    "name" : "test",
    "numjobs" : "32",
    "group_reporting" : "1",
    "iodepth" : "128",
    "fallocate" : "native",
    "runtime" : "120",
    "directory" : "/home/sevag/tmpfs",
    "nrfiles" : "64"
  },
  "jobs" : [
    {
      "jobname" : "jobs1",
      "groupid" : 0,
      "error" : 0,
      "eta" : 0,
      "elapsed" : 7,
      "job options" : {
        "filename_format" : "f$filenum"
      },
      "read" : {
        "io_bytes" : 0,
        "io_kbytes" : 0,
        "bw_bytes" : 0,
        "bw" : 0,
        "iops" : 0.000000,
        "runtime" : 0,
        "total_ios" : 0,
        "short_ios" : 0,
        "drop_ios" : 0,
        "slat_ns" : {
          "min" : 0,
          "max" : 0,
          "mean" : 0.000000,
          "stddev" : 0.000000,
          "N" : 0
        },
        "clat_ns" : {
          "min" : 0,
          "max" : 0,
          "mean" : 0.000000,
          "stddev" : 0.000000,
          "N" : 0
        },
        "lat_ns" : {
          "min" : 0,
          "max" : 0,
          "mean" : 0.000000,
          "stddev" : 0.000000,
          "N" : 0
        },
        "bw_min" : 0,
        "bw_max" : 0,
        "bw_agg" : 0.000000,
        "bw_mean" : 0.000000,
        "bw_dev" : 0.000000,
        "bw_samples" : 0,
        "iops_min" : 0,
        "iops_max" : 0,
        "iops_mean" : 0.000000,
        "iops_stddev" : 0.000000,
        "iops_samples" : 0
      },
      "write" : {
        "io_bytes" : 32212254720,
        "io_kbytes" : 31457280,
        "bw_bytes" : 5384863711,
        "bw" : 5258655,
        "iops" : 41083.249749,
        "runtime" : 5982,
        "total_ios" : 245760,
        "short_ios" : 0,
        "drop_ios" : 0,
        "slat_ns" : {
          "min" : 18699,
          "max" : 58904,
          "mean" : 23659.872270,
          "stddev" : 6471.713944,
          "N" : 245760
        },
        "clat_ns" : {
          "min" : 1435,
          "max" : 5701890,
          "mean" : 3089986.464201,
          "stddev" : 833391.718321,
          "N" : 245760,
          "percentile" : {
            "1.000000" : 2703360,
            "5.000000" : 2703360,
            "10.000000" : 2703360,
            "20.000000" : 2703360,
            "30.000000" : 2736128,
            "40.000000" : 2736128,
            "50.000000" : 2736128,
            "60.000000" : 2736128,
            "70.000000" : 2736128,
            "80.000000" : 2736128,
            "90.000000" : 5079040,
            "95.000000" : 5079040,
            "99.000000" : 5079040,
            "99.500000" : 5079040,
            "99.900000" : 5079040,
            "99.950000" : 5144576,
            "99.990000" : 5537792
          }
        },
        "lat_ns" : {
          "min" : 20985,
          "max" : 5748187,
          "mean" : 3113708.685816,
          "stddev" : 839799.413298,
          "N" : 245760
        },
        "bw_min" : 3212825,
        "bw_max" : 5974528,
        "bw_agg" : 99.525963,
        "bw_mean" : 5233728.090909,
        "bw_dev" : 1247028.986702,
        "bw_samples" : 11,
        "iops_min" : 25100,
        "iops_max" : 46676,
        "iops_mean" : 40888.454545,
        "iops_stddev" : 9742.440653,
        "iops_samples" : 11
      },
      "trim" : {
        "io_bytes" : 0,
        "io_kbytes" : 0,
        "bw_bytes" : 0,
        "bw" : 0,
        "iops" : 0.000000,
        "runtime" : 0,
        "total_ios" : 0,
        "short_ios" : 0,
        "drop_ios" : 0,
        "slat_ns" : {
          "min" : 0,
          "max" : 0,
          "mean" : 0.000000,
          "stddev" : 0.000000,
          "N" : 0
        },
        "clat_ns" : {
          "min" : 0,
          "max" : 0,
          "mean" : 0.000000,
          "stddev" : 0.000000,
          "N" : 0
        },
        "lat_ns" : {
          "min" : 0,
          "max" : 0,
          "mean" : 0.000000,
          "stddev" : 0.000000,
          "N" : 0
        },
        "bw_min" : 0,
        "bw_max" : 0,
        "bw_agg" : 0.000000,
        "bw_mean" : 0.000000,
        "bw_dev" : 0.000000,
        "bw_samples" : 0,
        "iops_min" : 0,
        "iops_max" : 0,
        "iops_mean" : 0.000000,
        "iops_stddev" : 0.000000,
        "iops_samples" : 0
      },
      "sync" : {
        "total_ios" : 0,
        "lat_ns" : {
          "min" : 0,
          "max" : 0,
          "mean" : 0.000000,
          "stddev" : 0.000000,
          "N" : 0
        }
      },
      "job_runtime" : 5982,
      "usr_cpu" : 10.498161,
      "sys_cpu" : 89.518556,
      "ctx" : 6,
      "majf" : 0,
      "minf" : 73,
      "iodepth_level" : {
        "1" : 0.100000,
        "2" : 0.100000,
        "4" : 0.100000,
        "8" : 0.100000,
        "16" : 0.100000,
        "32" : 0.100000,
        ">=64" : 99.974365
      },
      "iodepth_submit" : {
        "0" : 0.000000,
        "4" : 100.000000,
        "8" : 0.000000,
        "16" : 0.000000,
        "32" : 0.000000,
        "64" : 0.000000,
        ">=64" : 0.000000
      },
      "iodepth_complete" : {
        "0" : 0.000000,
        "4" : 99.999593,
        "8" : 0.000000,
        "16" : 0.000000,
        "32" : 0.000000,
        "64" : 0.000000,
        ">=64" : 0.100000
      },
      "latency_ns" : {
        "2" : 0.000000,
        "4" : 0.000000,
        "10" : 0.000000,
        "20" : 0.000000,
        "50" : 0.000000,
        "100" : 0.000000,
        "250" : 0.000000,
        "500" : 0.000000,
        "750" : 0.000000,
        "1000" : 0.000000
      },
      "latency_us" : {
        "2" : 0.010000,
        "4" : 0.000000,
        "10" : 0.000000,
        "20" : 0.000000,
        "50" : 0.010000,
        "100" : 0.010000,
        "250" : 0.010000,
        "500" : 0.010000,
        "750" : 0.010000,
        "1000" : 0.010000
      },
      "latency_ms" : {
        "2" : 0.019124,
        "4" : 84.427897,
        "10" : 15.533854,
        "20" : 0.000000,
        "50" : 0.000000,
        "100" : 0.000000,
        "250" : 0.000000,
        "500" : 0.000000,
        "750" : 0.000000,
        "1000" : 0.000000,
        "2000" : 0.000000,
        ">=2000" : 0.000000
      },
      "latency_depth" : 128,
      "latency_target" : 0,
      "latency_percentile" : 100.000000,
      "latency_window" : 0
    }
  ]
}
