{
  "fio version" : "fio-3.28",
  "timestamp" : 1690463224,
  "timestamp_ms" : 1690463224351,
  "time" : "Thu Jul 27 13:07:04 2023",
  "global options" : {
    "bs" : "32k",
    "ioengine" : "libaio",
    "rw" : "randwrite",
    "size" : "10G",
    "name" : "test",
    "numjobs" : "1",
    "group_reporting" : "1",
    "iodepth" : "128",
    "fallocate" : "native",
    "runtime" : "120",
    "directory" : "/home/sevag/ramdisk",
    "nrfiles" : "1"
  },
  "jobs" : [
    {
      "jobname" : "jobs1",
      "groupid" : 0,
      "error" : 0,
      "eta" : 0,
      "elapsed" : 5,
      "job options" : {
        "filename_format" : "f$filenum"
      },
      "read" : {
        "io_bytes" : 0,
        "io_kbytes" : 0,
        "bw_bytes" : 0,
        "bw" : 0,
        "iops" : 0.000000,
        "runtime" : 0,
        "total_ios" : 0,
        "short_ios" : 0,
        "drop_ios" : 0,
        "slat_ns" : {
          "min" : 0,
          "max" : 0,
          "mean" : 0.000000,
          "stddev" : 0.000000,
          "N" : 0
        },
        "clat_ns" : {
          "min" : 0,
          "max" : 0,
          "mean" : 0.000000,
          "stddev" : 0.000000,
          "N" : 0
        },
        "lat_ns" : {
          "min" : 0,
          "max" : 0,
          "mean" : 0.000000,
          "stddev" : 0.000000,
          "N" : 0
        },
        "bw_min" : 0,
        "bw_max" : 0,
        "bw_agg" : 0.000000,
        "bw_mean" : 0.000000,
        "bw_dev" : 0.000000,
        "bw_samples" : 0,
        "iops_min" : 0,
        "iops_max" : 0,
        "iops_mean" : 0.000000,
        "iops_stddev" : 0.000000,
        "iops_samples" : 0
      },
      "write" : {
        "io_bytes" : 10737418240,
        "io_kbytes" : 10485760,
        "bw_bytes" : 2613782434,
        "bw" : 2552521,
        "iops" : 79766.309640,
        "runtime" : 4108,
        "total_ios" : 327680,
        "short_ios" : 0,
        "drop_ios" : 0,
        "slat_ns" : {
          "min" : 6597,
          "max" : 55164,
          "mean" : 11788.651810,
          "stddev" : 3557.497650,
          "N" : 327680
        },
        "clat_ns" : {
          "min" : 1836,
          "max" : 4119935,
          "mean" : 1591289.990207,
          "stddev" : 455586.034643,
          "N" : 327680,
          "percentile" : {
            "1.000000" : 1105920,
            "5.000000" : 1105920,
            "10.000000" : 1105920,
            "20.000000" : 1122304,
            "30.000000" : 1122304,
            "40.000000" : 1122304,
            "50.000000" : 1990656,
            "60.000000" : 2007040,
            "70.000000" : 2023424,
            "80.000000" : 2023424,
            "90.000000" : 2039808,
            "95.000000" : 2039808,
            "99.000000" : 2039808,
            "99.500000" : 2056192,
            "99.900000" : 2965504,
            "99.950000" : 4046848,
            "99.990000" : 4112384
          }
        },
        "lat_ns" : {
          "min" : 9764,
          "max" : 4152009,
          "mean" : 1603168.388980,
          "stddev" : 459017.717836,
          "N" : 327680
        },
        "bw_min" : 1957312,
        "bw_max" : 3642304,
        "bw_agg" : 98.904185,
        "bw_mean" : 2524552.000000,
        "bw_dev" : 756627.237061,
        "bw_samples" : 8,
        "iops_min" : 61166,
        "iops_max" : 113822,
        "iops_mean" : 78892.250000,
        "iops_stddev" : 23644.601158,
        "iops_samples" : 8
      },
      "trim" : {
        "io_bytes" : 0,
        "io_kbytes" : 0,
        "bw_bytes" : 0,
        "bw" : 0,
        "iops" : 0.000000,
        "runtime" : 0,
        "total_ios" : 0,
        "short_ios" : 0,
        "drop_ios" : 0,
        "slat_ns" : {
          "min" : 0,
          "max" : 0,
          "mean" : 0.000000,
          "stddev" : 0.000000,
          "N" : 0
        },
        "clat_ns" : {
          "min" : 0,
          "max" : 0,
          "mean" : 0.000000,
          "stddev" : 0.000000,
          "N" : 0
        },
        "lat_ns" : {
          "min" : 0,
          "max" : 0,
          "mean" : 0.000000,
          "stddev" : 0.000000,
          "N" : 0
        },
        "bw_min" : 0,
        "bw_max" : 0,
        "bw_agg" : 0.000000,
        "bw_mean" : 0.000000,
        "bw_dev" : 0.000000,
        "bw_samples" : 0,
        "iops_min" : 0,
        "iops_max" : 0,
        "iops_mean" : 0.000000,
        "iops_stddev" : 0.000000,
        "iops_samples" : 0
      },
      "sync" : {
        "total_ios" : 0,
        "lat_ns" : {
          "min" : 0,
          "max" : 0,
          "mean" : 0.000000,
          "stddev" : 0.000000,
          "N" : 0
        }
      },
      "job_runtime" : 4107,
      "usr_cpu" : 8.692476,
      "sys_cpu" : 91.307524,
      "ctx" : 9,
      "majf" : 0,
      "minf" : 11,
      "iodepth_level" : {
        "1" : 0.100000,
        "2" : 0.100000,
        "4" : 0.100000,
        "8" : 0.100000,
        "16" : 0.100000,
        "32" : 0.100000,
        ">=64" : 99.980774
      },
      "iodepth_submit" : {
        "0" : 0.000000,
        "4" : 100.000000,
        "8" : 0.000000,
        "16" : 0.000000,
        "32" : 0.000000,
        "64" : 0.000000,
        ">=64" : 0.000000
      },
      "iodepth_complete" : {
        "0" : 0.000000,
        "4" : 99.999695,
        "8" : 0.000000,
        "16" : 0.000000,
        "32" : 0.000000,
        "64" : 0.000000,
        ">=64" : 0.100000
      },
      "latency_ns" : {
        "2" : 0.000000,
        "4" : 0.000000,
        "10" : 0.000000,
        "20" : 0.000000,
        "50" : 0.000000,
        "100" : 0.000000,
        "250" : 0.000000,
        "500" : 0.000000,
        "750" : 0.000000,
        "1000" : 0.000000
      },
      "latency_us" : {
        "2" : 0.010000,
        "4" : 0.000000,
        "10" : 0.000000,
        "20" : 0.010000,
        "50" : 0.010000,
        "100" : 0.010000,
        "250" : 0.010000,
        "500" : 0.010000,
        "750" : 0.010000,
        "1000" : 0.010000
      },
      "latency_ms" : {
        "2" : 50.665894,
        "4" : 49.242249,
        "10" : 0.056458,
        "20" : 0.000000,
        "50" : 0.000000,
        "100" : 0.000000,
        "250" : 0.000000,
        "500" : 0.000000,
        "750" : 0.000000,
        "1000" : 0.000000,
        "2000" : 0.000000,
        ">=2000" : 0.000000
      },
      "latency_depth" : 128,
      "latency_target" : 0,
      "latency_percentile" : 100.000000,
      "latency_window" : 0
    }
  ]
}
