{
  "fio version" : "fio-3.28",
  "timestamp" : 1690499738,
  "timestamp_ms" : 1690499738497,
  "time" : "Thu Jul 27 23:15:38 2023",
  "global options" : {
    "bs" : "512k",
    "ioengine" : "libaio",
    "rw" : "randread",
    "size" : "10G",
    "name" : "test",
    "numjobs" : "32",
    "group_reporting" : "1",
    "iodepth" : "128",
    "fallocate" : "native",
    "runtime" : "120",
    "directory" : "/home/sevag/ramdisk",
    "nrfiles" : "128"
  },
  "jobs" : [
    {
      "jobname" : "jobs1",
      "groupid" : 0,
      "error" : 0,
      "eta" : 0,
      "elapsed" : 3,
      "job options" : {
        "filename_format" : "f$filenum"
      },
      "read" : {
        "io_bytes" : 10737418240,
        "io_kbytes" : 10485760,
        "bw_bytes" : 5392977518,
        "bw" : 5266579,
        "iops" : 10286.288297,
        "runtime" : 1991,
        "total_ios" : 20480,
        "short_ios" : 0,
        "drop_ios" : 0,
        "slat_ns" : {
          "min" : 75705,
          "max" : 683598,
          "mean" : 95973.286865,
          "stddev" : 24268.377124,
          "N" : 20480
        },
        "clat_ns" : {
          "min" : 1568,
          "max" : 47521449,
          "mean" : 12172867.412744,
          "stddev" : 1707555.149558,
          "N" : 20480,
          "percentile" : {
            "1.000000" : 10551296,
            "5.000000" : 10551296,
            "10.000000" : 10551296,
            "20.000000" : 10682368,
            "30.000000" : 12386304,
            "40.000000" : 12386304,
            "50.000000" : 12386304,
            "60.000000" : 12386304,
            "70.000000" : 12517376,
            "80.000000" : 12517376,
            "90.000000" : 12648448,
            "95.000000" : 12779520,
            "99.000000" : 13434880,
            "99.500000" : 18219008,
            "99.900000" : 38010880,
            "99.950000" : 42729472,
            "99.990000" : 46399488
          }
        },
        "lat_ns" : {
          "min" : 84916,
          "max" : 48206385,
          "mean" : 12268910.821191,
          "stddev" : 1729246.248493,
          "N" : 20480
        },
        "bw_min" : 4733081,
        "bw_max" : 5234917,
        "bw_agg" : 96.182235,
        "bw_mean" : 5065514.000000,
        "bw_dev" : 287913.057014,
        "bw_samples" : 3,
        "iops_min" : 9244,
        "iops_max" : 10224,
        "iops_mean" : 9893.333333,
        "iops_stddev" : 562.371170,
        "iops_samples" : 3
      },
      "write" : {
        "io_bytes" : 0,
        "io_kbytes" : 0,
        "bw_bytes" : 0,
        "bw" : 0,
        "iops" : 0.000000,
        "runtime" : 0,
        "total_ios" : 0,
        "short_ios" : 0,
        "drop_ios" : 0,
        "slat_ns" : {
          "min" : 0,
          "max" : 0,
          "mean" : 0.000000,
          "stddev" : 0.000000,
          "N" : 0
        },
        "clat_ns" : {
          "min" : 0,
          "max" : 0,
          "mean" : 0.000000,
          "stddev" : 0.000000,
          "N" : 0
        },
        "lat_ns" : {
          "min" : 0,
          "max" : 0,
          "mean" : 0.000000,
          "stddev" : 0.000000,
          "N" : 0
        },
        "bw_min" : 0,
        "bw_max" : 0,
        "bw_agg" : 0.000000,
        "bw_mean" : 0.000000,
        "bw_dev" : 0.000000,
        "bw_samples" : 0,
        "iops_min" : 0,
        "iops_max" : 0,
        "iops_mean" : 0.000000,
        "iops_stddev" : 0.000000,
        "iops_samples" : 0
      },
      "trim" : {
        "io_bytes" : 0,
        "io_kbytes" : 0,
        "bw_bytes" : 0,
        "bw" : 0,
        "iops" : 0.000000,
        "runtime" : 0,
        "total_ios" : 0,
        "short_ios" : 0,
        "drop_ios" : 0,
        "slat_ns" : {
          "min" : 0,
          "max" : 0,
          "mean" : 0.000000,
          "stddev" : 0.000000,
          "N" : 0
        },
        "clat_ns" : {
          "min" : 0,
          "max" : 0,
          "mean" : 0.000000,
          "stddev" : 0.000000,
          "N" : 0
        },
        "lat_ns" : {
          "min" : 0,
          "max" : 0,
          "mean" : 0.000000,
          "stddev" : 0.000000,
          "N" : 0
        },
        "bw_min" : 0,
        "bw_max" : 0,
        "bw_agg" : 0.000000,
        "bw_mean" : 0.000000,
        "bw_dev" : 0.000000,
        "bw_samples" : 0,
        "iops_min" : 0,
        "iops_max" : 0,
        "iops_mean" : 0.000000,
        "iops_stddev" : 0.000000,
        "iops_samples" : 0
      },
      "sync" : {
        "total_ios" : 0,
        "lat_ns" : {
          "min" : 0,
          "max" : 0,
          "mean" : 0.000000,
          "stddev" : 0.000000,
          "N" : 0
        }
      },
      "job_runtime" : 1990,
      "usr_cpu" : 0.954774,
      "sys_cpu" : 98.944724,
      "ctx" : 2,
      "majf" : 0,
      "minf" : 16475,
      "iodepth_level" : {
        "1" : 0.100000,
        "2" : 0.100000,
        "4" : 0.100000,
        "8" : 0.100000,
        "16" : 0.100000,
        "32" : 0.156250,
        ">=64" : 99.692383
      },
      "iodepth_submit" : {
        "0" : 0.000000,
        "4" : 100.000000,
        "8" : 0.000000,
        "16" : 0.000000,
        "32" : 0.000000,
        "64" : 0.000000,
        ">=64" : 0.000000
      },
      "iodepth_complete" : {
        "0" : 0.000000,
        "4" : 99.995087,
        "8" : 0.000000,
        "16" : 0.000000,
        "32" : 0.000000,
        "64" : 0.000000,
        ">=64" : 0.100000
      },
      "latency_ns" : {
        "2" : 0.000000,
        "4" : 0.000000,
        "10" : 0.000000,
        "20" : 0.000000,
        "50" : 0.000000,
        "100" : 0.000000,
        "250" : 0.000000,
        "500" : 0.000000,
        "750" : 0.000000,
        "1000" : 0.000000
      },
      "latency_us" : {
        "2" : 0.010000,
        "4" : 0.000000,
        "10" : 0.000000,
        "20" : 0.000000,
        "50" : 0.000000,
        "100" : 0.010000,
        "250" : 0.010000,
        "500" : 0.014648,
        "750" : 0.014648,
        "1000" : 0.014648
      },
      "latency_ms" : {
        "2" : 0.058594,
        "4" : 0.117188,
        "10" : 0.351562,
        "20" : 98.959961,
        "50" : 0.449219,
        "100" : 0.000000,
        "250" : 0.000000,
        "500" : 0.000000,
        "750" : 0.000000,
        "1000" : 0.000000,
        "2000" : 0.000000,
        ">=2000" : 0.000000
      },
      "latency_depth" : 128,
      "latency_target" : 0,
      "latency_percentile" : 100.000000,
      "latency_window" : 0
    }
  ]
}
