{
  "fio version" : "fio-3.28",
  "timestamp" : 1690463060,
  "timestamp_ms" : 1690463060117,
  "time" : "Thu Jul 27 13:04:20 2023",
  "global options" : {
    "bs" : "32k",
    "ioengine" : "libaio",
    "rw" : "randwrite",
    "size" : "1G",
    "name" : "test",
    "numjobs" : "1",
    "group_reporting" : "1",
    "iodepth" : "128",
    "fallocate" : "native",
    "runtime" : "120",
    "directory" : "/home/sevag/fuse_boc",
    "nrfiles" : "1"
  },
  "jobs" : [
    {
      "jobname" : "jobs1",
      "groupid" : 0,
      "error" : 0,
      "eta" : 2147483647,
      "elapsed" : 1,
      "job options" : {
        "filename_format" : "f$filenum"
      },
      "read" : {
        "io_bytes" : 0,
        "io_kbytes" : 0,
        "bw_bytes" : 0,
        "bw" : 0,
        "iops" : 0.000000,
        "runtime" : 0,
        "total_ios" : 0,
        "short_ios" : 0,
        "drop_ios" : 0,
        "slat_ns" : {
          "min" : 0,
          "max" : 0,
          "mean" : 0.000000,
          "stddev" : 0.000000,
          "N" : 0
        },
        "clat_ns" : {
          "min" : 0,
          "max" : 0,
          "mean" : 0.000000,
          "stddev" : 0.000000,
          "N" : 0
        },
        "lat_ns" : {
          "min" : 0,
          "max" : 0,
          "mean" : 0.000000,
          "stddev" : 0.000000,
          "N" : 0
        },
        "bw_min" : 0,
        "bw_max" : 0,
        "bw_agg" : 0.000000,
        "bw_mean" : 0.000000,
        "bw_dev" : 0.000000,
        "bw_samples" : 0,
        "iops_min" : 0,
        "iops_max" : 0,
        "iops_mean" : 0.000000,
        "iops_stddev" : 0.000000,
        "iops_samples" : 0
      },
      "write" : {
        "io_bytes" : 1073741824,
        "io_kbytes" : 1048576,
        "bw_bytes" : 1900428007,
        "bw" : 1855886,
        "iops" : 57996.460177,
        "runtime" : 565,
        "total_ios" : 32768,
        "short_ios" : 0,
        "drop_ios" : 0,
        "slat_ns" : {
          "min" : 8844,
          "max" : 11396036,
          "mean" : 16561.514740,
          "stddev" : 136148.385055,
          "N" : 32768
        },
        "clat_ns" : {
          "min" : 1598,
          "max" : 61042281,
          "mean" : 1943493.793304,
          "stddev" : 1034396.118017,
          "N" : 32768,
          "percentile" : {
            "1.000000" : 1466368,
            "5.000000" : 1499136,
            "10.000000" : 1613824,
            "20.000000" : 1744896,
            "30.000000" : 1761280,
            "40.000000" : 1777664,
            "50.000000" : 1794048,
            "60.000000" : 1826816,
            "70.000000" : 1859584,
            "80.000000" : 1875968,
            "90.000000" : 1974272,
            "95.000000" : 2572288,
            "99.000000" : 4620288,
            "99.500000" : 5210112,
            "99.900000" : 13828096,
            "99.950000" : 13959168,
            "99.990000" : 36962304
          }
        },
        "lat_ns" : {
          "min" : 13983,
          "max" : 66717572,
          "mean" : 1960134.143677,
          "stddev" : 1098039.017771,
          "N" : 32768
        },
        "bw_min" : 1800512,
        "bw_max" : 1800512,
        "bw_agg" : 97.016266,
        "bw_mean" : 1800512.000000,
        "bw_dev" : 0.000000,
        "bw_samples" : 1,
        "iops_min" : 56266,
        "iops_max" : 56266,
        "iops_mean" : 56266.000000,
        "iops_stddev" : 0.000000,
        "iops_samples" : 1
      },
      "trim" : {
        "io_bytes" : 0,
        "io_kbytes" : 0,
        "bw_bytes" : 0,
        "bw" : 0,
        "iops" : 0.000000,
        "runtime" : 0,
        "total_ios" : 0,
        "short_ios" : 0,
        "drop_ios" : 0,
        "slat_ns" : {
          "min" : 0,
          "max" : 0,
          "mean" : 0.000000,
          "stddev" : 0.000000,
          "N" : 0
        },
        "clat_ns" : {
          "min" : 0,
          "max" : 0,
          "mean" : 0.000000,
          "stddev" : 0.000000,
          "N" : 0
        },
        "lat_ns" : {
          "min" : 0,
          "max" : 0,
          "mean" : 0.000000,
          "stddev" : 0.000000,
          "N" : 0
        },
        "bw_min" : 0,
        "bw_max" : 0,
        "bw_agg" : 0.000000,
        "bw_mean" : 0.000000,
        "bw_dev" : 0.000000,
        "bw_samples" : 0,
        "iops_min" : 0,
        "iops_max" : 0,
        "iops_mean" : 0.000000,
        "iops_stddev" : 0.000000,
        "iops_samples" : 0
      },
      "sync" : {
        "total_ios" : 0,
        "lat_ns" : {
          "min" : 0,
          "max" : 0,
          "mean" : 0.000000,
          "stddev" : 0.000000,
          "N" : 0
        }
      },
      "job_runtime" : 564,
      "usr_cpu" : 5.851064,
      "sys_cpu" : 81.205674,
      "ctx" : 12,
      "majf" : 0,
      "minf" : 14,
      "iodepth_level" : {
        "1" : 0.100000,
        "2" : 0.100000,
        "4" : 0.100000,
        "8" : 0.100000,
        "16" : 0.100000,
        "32" : 0.100000,
        ">=64" : 99.807739
      },
      "iodepth_submit" : {
        "0" : 0.000000,
        "4" : 100.000000,
        "8" : 0.000000,
        "16" : 0.000000,
        "32" : 0.000000,
        "64" : 0.000000,
        ">=64" : 0.000000
      },
      "iodepth_complete" : {
        "0" : 0.000000,
        "4" : 99.996936,
        "8" : 0.000000,
        "16" : 0.000000,
        "32" : 0.000000,
        "64" : 0.000000,
        ">=64" : 0.100000
      },
      "latency_ns" : {
        "2" : 0.000000,
        "4" : 0.000000,
        "10" : 0.000000,
        "20" : 0.000000,
        "50" : 0.000000,
        "100" : 0.000000,
        "250" : 0.000000,
        "500" : 0.000000,
        "750" : 0.000000,
        "1000" : 0.000000
      },
      "latency_us" : {
        "2" : 0.010000,
        "4" : 0.000000,
        "10" : 0.000000,
        "20" : 0.010000,
        "50" : 0.010000,
        "100" : 0.012207,
        "250" : 0.033569,
        "500" : 0.048828,
        "750" : 0.054932,
        "1000" : 0.054932
      },
      "latency_ms" : {
        "2" : 90.353394,
        "4" : 6.738281,
        "10" : 2.285767,
        "20" : 0.390625,
        "50" : 0.012207,
        "100" : 0.010000,
        "250" : 0.000000,
        "500" : 0.000000,
        "750" : 0.000000,
        "1000" : 0.000000,
        "2000" : 0.000000,
        ">=2000" : 0.000000
      },
      "latency_depth" : 128,
      "latency_target" : 0,
      "latency_percentile" : 100.000000,
      "latency_window" : 0
    }
  ]
}
