{
  "fio version" : "fio-3.28",
  "timestamp" : 1690503309,
  "timestamp_ms" : 1690503309926,
  "time" : "Fri Jul 28 00:15:09 2023",
  "global options" : {
    "bs" : "32k",
    "ioengine" : "libaio",
    "rw" : "read",
    "size" : "30G",
    "name" : "test",
    "numjobs" : "32",
    "group_reporting" : "1",
    "iodepth" : "128",
    "fallocate" : "native",
    "runtime" : "120",
    "directory" : "/home/sevag/fuse_boc",
    "nrfiles" : "1024"
  },
  "jobs" : [
    {
      "jobname" : "jobs1",
      "groupid" : 0,
      "error" : 24,
      "eta" : 2147483647,
      "elapsed" : 1,
      "job options" : {
        "filename_format" : "f$filenum"
      },
      "read" : {
        "io_bytes" : 33357824,
        "io_kbytes" : 32576,
        "bw_bytes" : 225390702,
        "bw" : 220108,
        "iops" : 6878.378378,
        "runtime" : 148,
        "total_ios" : 1018,
        "short_ios" : 0,
        "drop_ios" : 0,
        "slat_ns" : {
          "min" : 83506,
          "max" : 341085,
          "mean" : 104841.348723,
          "stddev" : 17498.082879,
          "N" : 1018
        },
        "clat_ns" : {
          "min" : 82178,
          "max" : 23589020,
          "mean" : 16778109.620825,
          "stddev" : 3529054.876676,
          "N" : 1018,
          "percentile" : {
            "1.000000" : 1761280,
            "5.000000" : 7438336,
            "10.000000" : 14745600,
            "20.000000" : 16908288,
            "30.000000" : 17432576,
            "40.000000" : 17432576,
            "50.000000" : 17432576,
            "60.000000" : 17694720,
            "70.000000" : 17694720,
            "80.000000" : 17956864,
            "90.000000" : 18219008,
            "95.000000" : 20316160,
            "99.000000" : 22151168,
            "99.500000" : 22675456,
            "99.900000" : 23199744,
            "99.950000" : 23461888,
            "99.990000" : 23461888
          }
        },
        "lat_ns" : {
          "min" : 166159,
          "max" : 23932220,
          "mean" : 16883400.362475,
          "stddev" : 3534123.880842,
          "N" : 1018
        },
        "bw_min" : 0,
        "bw_max" : 0,
        "bw_agg" : 0.000000,
        "bw_mean" : 0.000000,
        "bw_dev" : 0.000000,
        "bw_samples" : 0,
        "iops_min" : 0,
        "iops_max" : 0,
        "iops_mean" : 0.000000,
        "iops_stddev" : 0.000000,
        "iops_samples" : 0
      },
      "write" : {
        "io_bytes" : 0,
        "io_kbytes" : 0,
        "bw_bytes" : 0,
        "bw" : 0,
        "iops" : 0.000000,
        "runtime" : 0,
        "total_ios" : 0,
        "short_ios" : 0,
        "drop_ios" : 0,
        "slat_ns" : {
          "min" : 0,
          "max" : 0,
          "mean" : 0.000000,
          "stddev" : 0.000000,
          "N" : 0
        },
        "clat_ns" : {
          "min" : 0,
          "max" : 0,
          "mean" : 0.000000,
          "stddev" : 0.000000,
          "N" : 0
        },
        "lat_ns" : {
          "min" : 0,
          "max" : 0,
          "mean" : 0.000000,
          "stddev" : 0.000000,
          "N" : 0
        },
        "bw_min" : 0,
        "bw_max" : 0,
        "bw_agg" : 0.000000,
        "bw_mean" : 0.000000,
        "bw_dev" : 0.000000,
        "bw_samples" : 0,
        "iops_min" : 0,
        "iops_max" : 0,
        "iops_mean" : 0.000000,
        "iops_stddev" : 0.000000,
        "iops_samples" : 0
      },
      "trim" : {
        "io_bytes" : 0,
        "io_kbytes" : 0,
        "bw_bytes" : 0,
        "bw" : 0,
        "iops" : 0.000000,
        "runtime" : 0,
        "total_ios" : 0,
        "short_ios" : 0,
        "drop_ios" : 0,
        "slat_ns" : {
          "min" : 0,
          "max" : 0,
          "mean" : 0.000000,
          "stddev" : 0.000000,
          "N" : 0
        },
        "clat_ns" : {
          "min" : 0,
          "max" : 0,
          "mean" : 0.000000,
          "stddev" : 0.000000,
          "N" : 0
        },
        "lat_ns" : {
          "min" : 0,
          "max" : 0,
          "mean" : 0.000000,
          "stddev" : 0.000000,
          "N" : 0
        },
        "bw_min" : 0,
        "bw_max" : 0,
        "bw_agg" : 0.000000,
        "bw_mean" : 0.000000,
        "bw_dev" : 0.000000,
        "bw_samples" : 0,
        "iops_min" : 0,
        "iops_max" : 0,
        "iops_mean" : 0.000000,
        "iops_stddev" : 0.000000,
        "iops_samples" : 0
      },
      "sync" : {
        "total_ios" : 0,
        "lat_ns" : {
          "min" : 0,
          "max" : 0,
          "mean" : 0.000000,
          "stddev" : 0.000000,
          "N" : 0
        }
      },
      "job_runtime" : 147,
      "usr_cpu" : 2.721088,
      "sys_cpu" : 48.979592,
      "ctx" : 2038,
      "majf" : 0,
      "minf" : 1103,
      "iodepth_level" : {
        "1" : 0.100000,
        "2" : 0.196464,
        "4" : 0.392927,
        "8" : 0.785855,
        "16" : 1.571709,
        "32" : 3.143418,
        ">=64" : 93.811395
      },
      "iodepth_submit" : {
        "0" : 0.000000,
        "4" : 100.000000,
        "8" : 0.000000,
        "16" : 0.000000,
        "32" : 0.000000,
        "64" : 0.000000,
        ">=64" : 0.000000
      },
      "iodepth_complete" : {
        "0" : 0.000000,
        "4" : 99.887892,
        "8" : 0.000000,
        "16" : 0.000000,
        "32" : 0.000000,
        "64" : 0.000000,
        ">=64" : 0.112108
      },
      "latency_ns" : {
        "2" : 0.000000,
        "4" : 0.000000,
        "10" : 0.000000,
        "20" : 0.000000,
        "50" : 0.000000,
        "100" : 0.000000,
        "250" : 0.000000,
        "500" : 0.000000,
        "750" : 0.000000,
        "1000" : 0.000000
      },
      "latency_us" : {
        "2" : 0.000000,
        "4" : 0.000000,
        "10" : 0.000000,
        "20" : 0.000000,
        "50" : 0.000000,
        "100" : 0.098232,
        "250" : 0.000000,
        "500" : 0.098232,
        "750" : 0.196464,
        "1000" : 0.098232
      },
      "latency_ms" : {
        "2" : 0.687623,
        "4" : 1.375246,
        "10" : 4.223969,
        "20" : 87.426326,
        "50" : 5.795678,
        "100" : 0.000000,
        "250" : 0.000000,
        "500" : 0.000000,
        "750" : 0.000000,
        "1000" : 0.000000,
        "2000" : 0.000000,
        ">=2000" : 0.000000
      },
      "latency_depth" : 128,
      "latency_target" : 0,
      "latency_percentile" : 100.000000,
      "latency_window" : 0
    }
  ]
}
